{"jy-dfds":{"name":"佳源.东方都市","list":[{"title":"中洲花溪地，房型正气，两房朝南，厅南北通，全明采光","key":"A967024228","href":"https://jx.anjuke.com/prop/view/A967024228","details":{"home":"4室2厅","floor":"高层(共26层)","buildyear":2017},"area":110,"totalprice":120,"unitprice":10909,"date":"2017-9-13","imgs":["https://pic1.ajkimg.com/display/anjuke/fbde4c-%E9%87%91%E6%B3%B0%E5%9F%8E/d8a6b209c3980246468194e084596211-599x450.jpg?t=1","https://pic1.ajkimg.com/display/anjuke/0ba927-%E9%87%91%E6%B3%B0%E5%9F%8E/5688b036ac0f1c293dd350a4b9fda54f-599x450.jpg?t=1","https://pic1.ajkimg.com/display/anjuke/fc32b0-%E9%87%91%E6%B3%B0%E5%9F%8E/dd19e053102b085c292e253422c16ff3-599x450.jpg?t=1","https://pic1.ajkimg.com/display/anjuke/feb254-%E9%87%91%E6%B3%B0%E5%9F%8E/d730cba73f1e0b6335e6c6649f6d5f92-599x450.jpg?t=1","https://pic1.ajkimg.com/display/anjuke/f7ab14-%E9%87%91%E6%B3%B0%E5%9F%8E/46cba6bbb2880669ce7890742bae18e3-599x450.jpg?t=1","https://pic1.ajkimg.com/display/anjuke/27f36f-%E9%87%91%E6%B3%B0%E5%9F%8E/bff0edfa55cc7b211a2560d8d012def1-599x450.jpg?t=1","https://pic1.ajkimg.com/display/anjuke/b8e58a-%E9%87%91%E6%B3%B0%E5%9F%8E/5c7867c844799bb99948b7a6b31c5b16-599x450.jpg?t=1","https://pic1.ajkimg.com/display/anjuke/d55666-%E9%87%91%E6%B3%B0%E5%9F%8E/185120e7a4b6c784810bebf7fdb6a3ce-599x450.jpg?t=1","https://pic1.ajkimg.com/display/anjuke/e98323-%E9%87%91%E6%B3%B0%E5%9F%8E/3d15bc713fb36619be1f563fdc884a13-599x450.jpg?t=1"]},{"title":"海宁高/级中/学、鹃湖旁、地/铁/上/盖/现在来电更有优/惠","key":"A966968548","href":"https://jx.anjuke.com/prop/view/A966968548","details":{"home":"3室2厅","floor":"中层(共12层)","buildyear":2015},"area":89,"totalprice":136,"unitprice":15280,"date":"2017-9-13","imgs":["https://pic1.ajkimg.com/display/anjuke/c3f5dc-%E6%B0%B8%E5%8F%B0%E5%9C%B0%E4%BA%A7/c46bf3ce98d35bb70788e4199e1871b2-599x450.jpg?t=1","https://pic1.ajkimg.com/display/anjuke/a9e2c1-%E6%B0%B8%E5%8F%B0%E5%9C%B0%E4%BA%A7/8c81834cacf967183bedcc2cac0e67a1-599x450.jpg?t=1","https://pic1.ajkimg.com/display/anjuke/9c98be-%E6%B0%B8%E5%8F%B0%E5%9C%B0%E4%BA%A7/fd62236e3eebbb669ff053798faf90bf-599x450.jpg?t=1","https://pic1.ajkimg.com/display/anjuke/35ff52-%E6%B0%B8%E5%8F%B0%E5%9C%B0%E4%BA%A7/d2e59e6bbf8c432d4997c4a16600ffd5-599x450.jpg?t=1","https://pic1.ajkimg.com/display/anjuke/324a36-%E6%B0%B8%E5%8F%B0%E5%9C%B0%E4%BA%A7/33acfaa4447c88b2d2053a4b8ddb3f30-599x450.jpg?t=1","https://pic1.ajkimg.com/display/anjuke/275a0d-%E6%B0%B8%E5%8F%B0%E5%9C%B0%E4%BA%A7/14dc76ad1264d15ed0f28e1e67fb9efb-599x450.jpg?t=1"]},{"title":"总价40万，市中心政府旁，紧邻购物中心，名校驻守，可贷款。","key":"A966958692","href":"https://jx.anjuke.com/prop/view/A966958692","details":{"home":"1室1厅","floor":"中层(共21层)","buildyear":2016},"area":40,"totalprice":40,"unitprice":10000,"date":"2017-9-13","imgs":["https://pic1.ajkimg.com/display/anjuke/ae4282-%E4%BC%9F%E7%88%B1%E5%9C%B0%E4%BA%A7/1d41b67908980e30668a121736fc6ad0-599x450.jpg?t=1","https://pic1.ajkimg.com/display/anjuke/eaa358-%E4%BC%9F%E7%88%B1%E5%9C%B0%E4%BA%A7/6dfb9a2bd743cd6c7e2a23c06c83d6e6-599x450.jpg?t=1","https://pic1.ajkimg.com/display/anjuke/87acf6-%E4%BC%9F%E7%88%B1%E5%9C%B0%E4%BA%A7/dae471ead5da9e627a94228fbf686d1b-599x450.jpg?t=1","https://pic1.ajkimg.com/display/anjuke/c7a563-%E4%BC%9F%E7%88%B1%E5%9C%B0%E4%BA%A7/79b76146aa14c290d040655182baf8aa-599x450.jpg?t=1"]},{"title":"东方都市 位置好 楼层好 价格便宜 小区管理好 有意者来","key":"A966859022","href":"https://jx.anjuke.com/prop/view/A966859022","details":{"home":"3室2厅","floor":"高层(共24层)","buildyear":2013},"area":131,"totalprice":232,"unitprice":17709,"date":"2017-9-13","imgs":["https://pic1.ajkimg.com/display/anjuke/69a78b-%E7%8B%AC%E7%AB%8B%E7%BB%8F%E7%BA%AA%E4%BA%BA/c5692cd2426d81b6c8cb9b2274e74e7d-599x450.jpg?t=1","https://pic1.ajkimg.com/display/anjuke/422d83-%E7%8B%AC%E7%AB%8B%E7%BB%8F%E7%BA%AA%E4%BA%BA/d303aea403fbce98f46a6a0d1469127e-599x450.jpg?t=1","https://pic1.ajkimg.com/display/anjuke/a8401c-%E7%8B%AC%E7%AB%8B%E7%BB%8F%E7%BA%AA%E4%BA%BA/790497bbd9673ca5eb225d928a5358fb-599x450.jpg?t=1","https://pic1.ajkimg.com/display/anjuke/cccd9e-%E7%8B%AC%E7%AB%8B%E7%BB%8F%E7%BA%AA%E4%BA%BA/c22c6177ca37765d4801feaf543f4186-599x450.jpg?t=1","https://pic1.ajkimg.com/display/anjuke/caa0c6-%E7%8B%AC%E7%AB%8B%E7%BB%8F%E7%BA%AA%E4%BA%BA/88e5f7201380424b2f596caa2a64c450-599x450.jpg?t=1","https://pic1.ajkimg.com/display/anjuke/7651d4-%E7%8B%AC%E7%AB%8B%E7%BB%8F%E7%BA%AA%E4%BA%BA/45c4a9ec1a43e27ea777c6f55079b0f6-599x450.jpg?t=1","https://pic1.ajkimg.com/display/anjuke/f2d482-%E7%8B%AC%E7%AB%8B%E7%BB%8F%E7%BA%AA%E4%BA%BA/1e9a451e0a310b0780c9394e23f8b7fa-599x450.jpg?t=1","https://pic1.ajkimg.com/display/anjuke/887d85-%E7%8B%AC%E7%AB%8B%E7%BB%8F%E7%BA%AA%E4%BA%BA/9482e7e68f03bd2334fc3f58ff759c01-599x450.jpg?t=1","https://pic1.ajkimg.com/display/anjuke/126185-%E7%8B%AC%E7%AB%8B%E7%BB%8F%E7%BA%AA%E4%BA%BA/4d3e8b76c73fdb1499afd01b8f9c0416-599x450.jpg?t=1"]},{"title":"全新毛坯，景观楼层，户型正气，边套采光好，急卖","key":"A966822425","href":"https://jx.anjuke.com/prop/view/A966822425","details":{"home":"3室2厅","floor":"高层(共29层)","buildyear":2016},"area":117,"totalprice":180,"unitprice":15384,"date":"2017-9-13","imgs":["https://pic1.ajkimg.com/display/anjuke/811027-/c2730a6839d328a3a6c4a567080b338a-599x450.jpg?t=1","https://pic1.ajkimg.com/display/anjuke/5d8f17-/d7b05adf0512fd6692ecd5d77797455c-599x450.jpg?t=1"]},{"title":"《真》实验好房子","key":"A966787951","href":"https://jx.anjuke.com/prop/view/A966787951","details":{"home":"3室2厅","floor":"中层(共26层)","buildyear":2014},"area":128,"totalprice":188,"unitprice":14687,"date":"2017-9-13","imgs":["https://pic1.ajkimg.com/display/anjuke/494eed-%E7%8B%AC%E7%AB%8B%E7%BB%8F%E7%BA%AA%E4%BA%BA/6698726c3114a621c3bce688711ed871-599x450.jpg?t=1","https://pic1.ajkimg.com/display/anjuke/9a650c-%E7%8B%AC%E7%AB%8B%E7%BB%8F%E7%BA%AA%E4%BA%BA/110a05a3ff8ac13f6e1dfaa18a668cd2-599x450.jpg?t=1","https://pic1.ajkimg.com/display/anjuke/211c86-%E7%8B%AC%E7%AB%8B%E7%BB%8F%E7%BA%AA%E4%BA%BA/6773679db2fbe4af99908a802cb8aa59-599x450.jpg?t=1","https://pic1.ajkimg.com/display/anjuke/fd6200-%E7%8B%AC%E7%AB%8B%E7%BB%8F%E7%BA%AA%E4%BA%BA/5923b02dd70e18610725b623d39d460c-599x450.jpg?t=1","https://pic1.ajkimg.com/display/anjuke/a03baa-%E7%8B%AC%E7%AB%8B%E7%BB%8F%E7%BA%AA%E4%BA%BA/b5ca07a9c87f1f9d9ca7d182f24d6f1e-599x450.jpg?t=1","https://pic1.ajkimg.com/display/anjuke/114892-%E7%8B%AC%E7%AB%8B%E7%BB%8F%E7%BA%AA%E4%BA%BA/c2e71597b26b04deaeb5a5e20f1e93af-599x450.jpg?t=1","https://pic1.ajkimg.com/display/anjuke/c5964b-%E7%8B%AC%E7%AB%8B%E7%BB%8F%E7%BA%AA%E4%BA%BA/a80eb8c33ea976e30d5a71e723ad7a31-599x450.jpg?t=1","https://pic1.ajkimg.com/display/anjuke/21d520-%E7%8B%AC%E7%AB%8B%E7%BB%8F%E7%BA%AA%E4%BA%BA/a5fbd9f62827d4d7f71fc44460b58bf5-599x450.jpg?t=1"]},{"title":"万达旁/首付30万/精装/包租/现房/低首付/低总价/地段好","key":"A966658622","href":"https://jx.anjuke.com/prop/view/A966658622","details":{"home":"2室2厅","floor":"中层(共18层)","buildyear":2015},"area":99,"totalprice":105,"unitprice":10606,"date":"2017-9-13","imgs":["https://pic1.ajkimg.com/display/anjuke/7b9fe3-%E5%AE%9A%E5%B8%86%E5%9C%B0%E4%BA%A7%20%E5%98%89%E5%85%B4%E5%88%86%E5%85%AC%E5%8F%B8/dc4fea96496857069e7e920dddcf0bd9-599x450.jpg?t=1","https://pic1.ajkimg.com/display/anjuke/44b153-%E5%AE%9A%E5%B8%86%E5%9C%B0%E4%BA%A7%20%E5%98%89%E5%85%B4%E5%88%86%E5%85%AC%E5%8F%B8/b353a492e172897d1e97e08b28d59572-599x450.jpg?t=1","https://pic1.ajkimg.com/display/anjuke/2e3bbc-%E5%AE%9A%E5%B8%86%E5%9C%B0%E4%BA%A7%20%E5%98%89%E5%85%B4%E5%88%86%E5%85%AC%E5%8F%B8/6fd563abc9b9ea3ea120a8740a9a27c2-599x450.jpg?t=1","https://pic1.ajkimg.com/display/anjuke/cfc1ac-%E5%AE%9A%E5%B8%86%E5%9C%B0%E4%BA%A7%20%E5%98%89%E5%85%B4%E5%88%86%E5%85%AC%E5%8F%B8/b2cece722d816b86c02a600fa866ea06-599x450.jpg?t=1","https://pic1.ajkimg.com/display/anjuke/ea8813-%E5%AE%9A%E5%B8%86%E5%9C%B0%E4%BA%A7%20%E5%98%89%E5%85%B4%E5%88%86%E5%85%AC%E5%8F%B8/b041b009321eefd355d67ae4566e02aa-599x450.jpg?t=1","https://pic1.ajkimg.com/display/anjuke/22fdc7-%E5%AE%9A%E5%B8%86%E5%9C%B0%E4%BA%A7%20%E5%98%89%E5%85%B4%E5%88%86%E5%85%AC%E5%8F%B8/c40c4cc616b660e1041c84f086cc9c60-599x450.jpg?t=1","https://pic1.ajkimg.com/display/anjuke/5df019-%E5%AE%9A%E5%B8%86%E5%9C%B0%E4%BA%A7%20%E5%98%89%E5%85%B4%E5%88%86%E5%85%AC%E5%8F%B8/dfbb7390fa9e19f457e3658269fd36fc-599x450.jpg?t=1"]},{"title":"隆重开盘吴越学府 北师大名校 地铁口高铁旁 市中心品质洋房","key":"A966644516","href":"https://jx.anjuke.com/prop/view/A966644516","details":{"home":"3室2厅","floor":"高层(共25层)","buildyear":2016},"area":90,"totalprice":125,"unitprice":13888,"date":"2017-9-13","imgs":["https://pic1.ajkimg.com/display/anjuke/502926-%E6%B0%B8%E5%8F%B0%E5%9C%B0%E4%BA%A7/f429cb448def04a22ad443628eec60ae-599x450.jpg?t=1","https://pic1.ajkimg.com/display/anjuke/6bf9c5-%E6%B0%B8%E5%8F%B0%E5%9C%B0%E4%BA%A7/1047a9573a9d6f815c9971921bd2da8e-599x450.jpg?t=1","https://pic1.ajkimg.com/display/anjuke/426454-%E6%B0%B8%E5%8F%B0%E5%9C%B0%E4%BA%A7/c2f40fefcafa8bf353adf19d454d4e23-599x450.jpg?t=1","https://pic1.ajkimg.com/display/anjuke/88a31d-%E6%B0%B8%E5%8F%B0%E5%9C%B0%E4%BA%A7/33f3aa5140d71d48b2065536a959323a-599x450.jpg?t=1","https://pic1.ajkimg.com/display/anjuke/29ccf4-%E6%B0%B8%E5%8F%B0%E5%9C%B0%E4%BA%A7/8cdb26b75f8e5b1f751e2f4bcf3f76e2-599x450.jpg?t=1","https://pic1.ajkimg.com/display/anjuke/27f10c-%E6%B0%B8%E5%8F%B0%E5%9C%B0%E4%BA%A7/a8cd839bfaddaebbaae1d4c9f725368b-599x450.jpg?t=1","https://pic1.ajkimg.com/display/anjuke/ecd4c5-%E6%B0%B8%E5%8F%B0%E5%9C%B0%E4%BA%A7/a66978a5a783ecdd0ed34e35a67a3a57-599x450.jpg?t=1"]},{"title":"科技城小学 房东急售！！！ 可看同户型 随时方便","key":"A966422313","href":"https://jx.anjuke.com/prop/view/A966422313","details":{"home":"3室2厅","floor":"高层(共29层)","buildyear":2016},"area":117,"totalprice":176,"unitprice":15042,"date":"2017-9-13","imgs":["https://pic1.ajkimg.com/display/anjuke/b64c7d-/d309117adfd312e58d19b22f30505280-599x450.jpg?t=1","https://pic1.ajkimg.com/display/anjuke/811027-/c2730a6839d328a3a6c4a567080b338a-599x450.jpg?t=1","https://pic1.ajkimg.com/display/anjuke/5d8f17-/d7b05adf0512fd6692ecd5d77797455c-599x450.jpg?t=1","https://pic1.ajkimg.com/display/anjuke/597673-/f92a2f4ec7dbf2cc9f2d2693c679dc12-599x450.jpg?t=1","https://pic1.ajkimg.com/display/anjuke/b2d9fb-/271f256d142ecf11d6d46501ad523aa1-599x450.jpg?t=1"]},{"title":"嘉兴市内 简约现房 东方人的都市 东方都市 够大 才舒适","key":"A966397842","href":"https://jx.anjuke.com/prop/view/A966397842","details":{"home":"3室2厅","floor":"高层(共22层)","buildyear":2016},"area":128,"totalprice":109,"unitprice":8500,"date":"2017-9-13","imgs":[null,"https://pic1.ajkimg.com/display/anjuke/80ed5a-%E6%B0%B8%E5%8F%B0%E5%9C%B0%E4%BA%A7/d641fb86125f535d06156ca71b010da5-599x450.jpg?t=1","https://pic1.ajkimg.com/display/anjuke/53be55-%E6%B0%B8%E5%8F%B0%E5%9C%B0%E4%BA%A7/c71ccf335f9ce4a0cd8a822330e446dd-599x450.jpg?t=1","https://pic1.ajkimg.com/display/anjuke/1d6df2-%E6%B0%B8%E5%8F%B0%E5%9C%B0%E4%BA%A7/e27da589e89534b32ddfdb326d8588c7-599x450.jpg?t=1","https://pic1.ajkimg.com/display/anjuke/50d614-%E6%B0%B8%E5%8F%B0%E5%9C%B0%E4%BA%A7/9b909aae9e81303630601da1d48a51ad-599x450.jpg?t=1","https://pic1.ajkimg.com/display/anjuke/096f02-%E6%B0%B8%E5%8F%B0%E5%9C%B0%E4%BA%A7/f1c3336c5b05b2f1c4cb378f0efd8cdc-599x450.jpg?t=1","https://pic1.ajkimg.com/display/anjuke/862895-%E6%B0%B8%E5%8F%B0%E5%9C%B0%E4%BA%A7/82585efab1d14508147a61184032e421-599x450.jpg?t=1","https://pic1.ajkimg.com/display/anjuke/e65d1e-%E6%B0%B8%E5%8F%B0%E5%9C%B0%E4%BA%A7/e88fd5230fa0fe4ecd5b50100f952944-599x450.jpg?t=1"]}],"trend":{"community":[{"201410":"0"},{"201411":"0"},{"201412":"0"},{"201501":"0"},{"201502":"0"},{"201503":"0"},{"201504":"0"},{"201505":"0"},{"201506":"0"},{"201507":"0"},{"201508":"0"},{"201509":"0"},{"201510":"0"},{"201511":"0"},{"201512":"0"},{"201601":"0"},{"201602":"0"},{"201603":"0"},{"201604":"0"},{"201605":"0"},{"201606":"0"},{"201607":"10077"},{"201608":"9473"},{"201609":"9662"},{"201610":"10690"},{"201611":"10969"},{"201612":"10762"},{"201701":"11161"},{"201702":"11381"},{"201703":"11176"},{"201704":"11795"},{"201705":"12605"},{"201706":"14055"},{"201707":"14491"},{"201708":"14592"},{"201709":"14614"}],"area":[{"201410":"7390"},{"201411":"7801"},{"201412":"0"},{"201501":"0"},{"201502":"0"},{"201503":"0"},{"201504":"4482"},{"201505":"5888"},{"201506":"6049"},{"201507":"7316"},{"201508":"6928"},{"201509":"6286"},{"201510":"6410"},{"201511":"6666"},{"201512":"4259"},{"201601":"6076"},{"201602":"5709"},{"201603":"5833"},{"201604":"6520"},{"201605":"7164"},{"201606":"7142"},{"201607":"7142"},{"201608":"7507"},{"201609":"7818"},{"201610":"9042"},{"201611":"9590"},{"201612":"9079"},{"201701":"9209"},{"201702":"9366"},{"201703":"9901"},{"201704":"9666"},{"201705":"10343"},{"201706":"10512"},{"201707":"10839"},{"201708":"11062"},{"201709":"11226"}],"comm_midchange":"0.00154985","area_midchange":"0.0148255"}},"hrhy":{"name":"宏润花园","list":[{"title":"宏润花园：店内有钥匙、婚房装修全送、南北直通、实验+东北师大","key":"A966944986","href":"https://jx.anjuke.com/prop/view/A966944986","details":{"home":"2室2厅","floor":"中层(共18层)","buildyear":2012},"area":89,"totalprice":130,"unitprice":14606,"date":"2017-9-13","imgs":["https://pic1.ajkimg.com/display/anjuke/53ee0c-%E6%B0%B8%E5%8F%B0%E5%9C%B0%E4%BA%A7/269c241e92b0ecf5b1802e09c5a57a8c-599x450.jpg?t=1","https://pic1.ajkimg.com/display/anjuke/ec1e1e-%E6%B0%B8%E5%8F%B0%E5%9C%B0%E4%BA%A7/aa5103cea77399a58761d3d9f3f5a8c0-599x450.jpg?t=1","https://pic1.ajkimg.com/display/anjuke/13d66a-%E6%B0%B8%E5%8F%B0%E5%9C%B0%E4%BA%A7/b2e76f00b545cd633e44fb1b7e25df63-599x450.jpg?t=1","https://pic1.ajkimg.com/display/anjuke/e34b6c-%E6%B0%B8%E5%8F%B0%E5%9C%B0%E4%BA%A7/ad06cfedf3a5f28b325d69ca9bbd1fd4-599x450.jpg?t=1","https://pic1.ajkimg.com/display/anjuke/66309a-%E6%B0%B8%E5%8F%B0%E5%9C%B0%E4%BA%A7/5aa9dd38c1d5110e2bfe3face0e5055c-599x450.jpg?t=1","https://pic1.ajkimg.com/display/anjuke/e135a7-%E6%B0%B8%E5%8F%B0%E5%9C%B0%E4%BA%A7/2b08a0b4ff0039c0114de4df35db9db9-599x450.jpg?t=1","https://pic1.ajkimg.com/display/anjuke/5af645-%E6%B0%B8%E5%8F%B0%E5%9C%B0%E4%BA%A7/74d75926745144e3c5bb18ba6d5dd5be-599x450.jpg?t=1"]},{"title":"地段不多说《双朝南，采光通风极好》《63万精装现房》繁华地段","key":"A966803075","href":"https://jx.anjuke.com/prop/view/A966803075","details":{"home":"2室2厅","floor":"中层(共13层)","buildyear":2014},"area":73,"totalprice":63,"unitprice":8571,"date":"2017-9-13","imgs":["https://pic1.ajkimg.com/display/anjuke/0cec36-%E7%9B%8A%E8%81%94%E5%9C%B0%E4%BA%A7/1b7f28e1bec8ac7472647cc0bda501dd-599x450.jpg?t=1","https://pic1.ajkimg.com/display/anjuke/a7e3f1-%E7%9B%8A%E8%81%94%E5%9C%B0%E4%BA%A7/84264253f03842a60620af0284f215e4-599x450.jpg?t=1","https://pic1.ajkimg.com/display/anjuke/96c8a9-%E7%9B%8A%E8%81%94%E5%9C%B0%E4%BA%A7/71bfa033e4a99827f0893563c227f2ac-599x450.jpg?t=1","https://pic1.ajkimg.com/display/anjuke/0b24c7-%E7%9B%8A%E8%81%94%E5%9C%B0%E4%BA%A7/25c0134ffd9566a88b3fc9973da722d4-599x450.jpg?t=1","https://pic1.ajkimg.com/display/anjuke/916e47-%E7%9B%8A%E8%81%94%E5%9C%B0%E4%BA%A7/68ce9c54eb1cf5562fb869562b27e56a-599x450.jpg?t=1","https://pic1.ajkimg.com/display/anjuke/ca0129-%E7%9B%8A%E8%81%94%E5%9C%B0%E4%BA%A7/02e33d48f1012eb1410cc61b994ecd85-599x450.jpg?t=1","https://pic1.ajkimg.com/display/anjuke/5f18bc-%E7%9B%8A%E8%81%94%E5%9C%B0%E4%BA%A7/0562b1354f499403c87a710be27a57d1-599x450.jpg?t=1","https://pic1.ajkimg.com/display/anjuke/f5c493-%E7%9B%8A%E8%81%94%E5%9C%B0%E4%BA%A7/43ae60b1db8929f2d1fc732f0f9fdcfe-599x450.jpg?t=1","https://pic1.ajkimg.com/display/anjuke/1fa9fb-%E7%9B%8A%E8%81%94%E5%9C%B0%E4%BA%A7/74024d8d34680b77c38d450a9e905b52-599x450.jpg?t=1"]},{"title":"嘉兴市中心 万达板块 吴越学府 实验小学 配套成熟 交通方便","key":"A966792579","href":"https://jx.anjuke.com/prop/view/A966792579","details":{"home":"3室2厅","floor":"中层(共29层)","buildyear":2015},"area":90,"totalprice":106,"unitprice":11777,"date":"2017-9-13","imgs":["https://pic1.ajkimg.com/display/anjuke/4f646a-%E5%86%B3%E8%BF%B9%E6%88%BF%E5%9C%B0%E4%BA%A7/81ffc251478704fcec44ec2c801c4dbc-599x450.jpg?t=1","https://pic1.ajkimg.com/display/anjuke/f66a66-%E5%86%B3%E8%BF%B9%E6%88%BF%E5%9C%B0%E4%BA%A7/117388b2d01dde14ab8159ea536526b5-599x450.jpg?t=1","https://pic1.ajkimg.com/display/anjuke/3f98c6-%E5%86%B3%E8%BF%B9%E6%88%BF%E5%9C%B0%E4%BA%A7/14cd01da9936e524530c4c5491489155-599x450.jpg?t=1","https://pic1.ajkimg.com/display/anjuke/c18189-%E5%86%B3%E8%BF%B9%E6%88%BF%E5%9C%B0%E4%BA%A7/c40a0253ed83bf5650722991bf676722-599x450.jpg?t=1","https://pic1.ajkimg.com/display/anjuke/592527-%E5%86%B3%E8%BF%B9%E6%88%BF%E5%9C%B0%E4%BA%A7/1f3fd02b80f2994832a6b7d9ff32d28c-599x450.jpg?t=1","https://pic1.ajkimg.com/display/anjuke/bbf5a5-%E5%86%B3%E8%BF%B9%E6%88%BF%E5%9C%B0%E4%BA%A7/3d259fda02ddc948a040a072537fc2bb-599x450.jpg?t=1","https://pic1.ajkimg.com/display/anjuke/86e1a8-%E5%86%B3%E8%BF%B9%E6%88%BF%E5%9C%B0%E4%BA%A7/3994ff4764bb49221a73767e3cd1e775-599x450.jpg?t=1"]},{"title":"中州花溪地 万达旁+双学.区+小3房+三面公园环抱+嘉兴一中","key":"A966743088","href":"https://jx.anjuke.com/prop/view/A966743088","details":{"home":"3室2厅","floor":"高层(共11层)","buildyear":2017},"area":90,"totalprice":96,"unitprice":10666,"date":"2017-9-13","imgs":["https://pic1.ajkimg.com/display/anjuke/c60dbd-%E6%B0%B8%E5%AE%BF%E6%88%BF%E4%BA%A7/2635459c77863cec410fc22f95e16a20-599x450.jpg?t=1","https://pic1.ajkimg.com/display/anjuke/d35cf1-%E6%B0%B8%E5%AE%BF%E6%88%BF%E4%BA%A7/d2dbb8d0cd40ccd35ef1b47e6ef57bdc-599x450.jpg?t=1","https://pic1.ajkimg.com/display/anjuke/0d5199-%E6%B0%B8%E5%AE%BF%E6%88%BF%E4%BA%A7/e6521c7edac1f67709423079aaef3b32-599x450.jpg?t=1","https://pic1.ajkimg.com/display/anjuke/0eff49-%E6%B0%B8%E5%AE%BF%E6%88%BF%E4%BA%A7/f7daac921eb146a34445e38df6761517-599x450.jpg?t=1","https://pic1.ajkimg.com/display/anjuke/df322d-%E6%B0%B8%E5%AE%BF%E6%88%BF%E4%BA%A7/4c45a946ead028ee7233bb3d26534ee1-599x450.jpg?t=1","https://pic1.ajkimg.com/display/anjuke/20a529-%E6%B0%B8%E5%AE%BF%E6%88%BF%E4%BA%A7/7165c2757c3e096b4f837faa78905cdc-599x450.jpg?t=1","https://pic1.ajkimg.com/display/anjuke/001f58-%E6%B0%B8%E5%AE%BF%E6%88%BF%E4%BA%A7/4ccd7801a42a9e54ba8c2035e2657942-599x450.jpg?t=1","https://pic1.ajkimg.com/display/anjuke/039939-%E6%B0%B8%E5%AE%BF%E6%88%BF%E4%BA%A7/e411cadd4ccf8589212b7790a883624f-599x450.jpg?t=1","https://pic1.ajkimg.com/display/anjuke/6caf07-%E6%B0%B8%E5%AE%BF%E6%88%BF%E4%BA%A7/e1ac28cf32f19704e4e579d9b1f907b7-599x450.jpg?t=1"]},{"title":"宏润花园除去装修低于市场价十几万、可拎包入住、房东诚心出售！","key":"A966708461","href":"https://jx.anjuke.com/prop/view/A966708461","details":{"home":"2室2厅","floor":"低层(共15层)","buildyear":2013},"area":95,"totalprice":121,"unitprice":12736,"date":"2017-9-13","imgs":["https://pic1.ajkimg.com/display/anjuke/e6c8a1-%E6%B0%B8%E5%8F%B0%E5%9C%B0%E4%BA%A7/2693b2b3b56f9d5f9e21da88dbce2989-599x450.jpg?t=1","https://pic1.ajkimg.com/display/anjuke/3e35b2-%E6%B0%B8%E5%8F%B0%E5%9C%B0%E4%BA%A7/eb0f4f13f2165e7d0de6afed49e4af92-599x450.jpg?t=1","https://pic1.ajkimg.com/display/anjuke/a07fea-%E6%B0%B8%E5%8F%B0%E5%9C%B0%E4%BA%A7/8c8e1261f7582e530e5fe8b347473807-599x450.jpg?t=1","https://pic1.ajkimg.com/display/anjuke/13af66-%E6%B0%B8%E5%8F%B0%E5%9C%B0%E4%BA%A7/44a2d3a80f7b56972a49e05a0c013482-599x450.jpg?t=1","https://pic1.ajkimg.com/display/anjuke/1f1b4e-%E6%B0%B8%E5%8F%B0%E5%9C%B0%E4%BA%A7/4065c99cef65ec3f417f2546daf027f5-599x450.jpg?t=1","https://pic1.ajkimg.com/display/anjuke/0b3076-%E6%B0%B8%E5%8F%B0%E5%9C%B0%E4%BA%A7/143507bd5b8ef49ed73cca5126cb2aea-599x450.jpg?t=1"]},{"title":"吴越学府政府重点打造的万达科技城板块，户型格局方正！","key":"A966629552","href":"https://jx.anjuke.com/prop/view/A966629552","details":{"home":"3室2厅","floor":"高层(共16层)","buildyear":2017},"area":90,"totalprice":130,"unitprice":14444,"date":"2017-9-13","imgs":["https://pic1.ajkimg.com/display/anjuke/211fcd-%E5%AE%9D%E5%8A%B2%E6%88%BF%E4%BA%A7/a0cae1dd39368df8b7e837f1ff07eeb1-599x450.jpg?t=1","https://pic1.ajkimg.com/display/anjuke/5928d8-%E5%AE%9D%E5%8A%B2%E6%88%BF%E4%BA%A7/3322773061f46780610f0123f4129b53-599x450.jpg?t=1","https://pic1.ajkimg.com/display/anjuke/7d575d-%E5%AE%9D%E5%8A%B2%E6%88%BF%E4%BA%A7/05f9453b3a1846c329167f67e2e9ff99-599x450.jpg?t=1","https://pic1.ajkimg.com/display/anjuke/85b276-%E5%AE%9D%E5%8A%B2%E6%88%BF%E4%BA%A7/95fc4eafa98a755a1ae3dd7b3931bcb2-599x450.jpg?t=1","https://pic1.ajkimg.com/display/anjuke/b8613d-%E5%AE%9D%E5%8A%B2%E6%88%BF%E4%BA%A7/e9f0f39906e18bec71f22589be4f76a1-599x450.jpg?t=1","https://pic1.ajkimg.com/display/anjuke/ccdfd9-%E5%AE%9D%E5%8A%B2%E6%88%BF%E4%BA%A7/eeb1b5c21715e8d53758408801be0c90-599x450.jpg?t=1","https://pic1.ajkimg.com/display/anjuke/c984d5-%E5%AE%9D%E5%8A%B2%E6%88%BF%E4%BA%A7/eb85cc9bdde5afd2655eed1b7161f603-599x450.jpg?t=1"]},{"title":"宏润花园 房东急售 低于市场价 小区唯一 一套性价比高的房源","key":"A966608383","href":"https://jx.anjuke.com/prop/view/A966608383","details":{"home":"3室2厅","floor":"高层(共30层)","buildyear":2016},"area":130,"totalprice":180,"unitprice":13846,"date":"2017-9-13","imgs":["https://pic1.ajkimg.com/display/anjuke/a23ae8-%E5%AE%9A%E5%B8%86%E5%9C%B0%E4%BA%A7/a7b373610fbc2638a5eae3fce2784ae6-599x450.jpg?t=1","https://pic1.ajkimg.com/display/anjuke/fa6807-%E5%AE%9A%E5%B8%86%E5%9C%B0%E4%BA%A7/a388c754e0b639e8b834523aebb0ad09-599x450.jpg?t=1","https://pic1.ajkimg.com/display/anjuke/7a0d64-%E5%AE%9A%E5%B8%86%E5%9C%B0%E4%BA%A7/39d63af25a698700174cc629e73d7542-599x450.jpg?t=1","https://pic1.ajkimg.com/display/anjuke/453330-%E5%AE%9A%E5%B8%86%E5%9C%B0%E4%BA%A7/eff0e53a63245c63e22ce84d166fd053-599x450.jpg?t=1","https://pic1.ajkimg.com/display/anjuke/613ae5-%E5%AE%9A%E5%B8%86%E5%9C%B0%E4%BA%A7/17c5b4b3adb4e3dff5c22b3b7dba0adb-599x450.jpg?t=1","https://pic1.ajkimg.com/display/anjuke/cb57f8-%E5%AE%9A%E5%B8%86%E5%9C%B0%E4%BA%A7/4458024f42f9883c85dd710d272fc03a-599x450.jpg?t=1","https://pic1.ajkimg.com/display/anjuke/dc0012-%E5%AE%9A%E5%B8%86%E5%9C%B0%E4%BA%A7/a0255cfd1a35812952c09bab440498fb-599x450.jpg?t=1","https://pic1.ajkimg.com/display/anjuke/986cf7-%E5%AE%9A%E5%B8%86%E5%9C%B0%E4%BA%A7/ea2f8a79a3250d49d8f222a125fc8eeb-599x450.jpg?t=1","https://pic1.ajkimg.com/display/anjuke/ba9c6e-%E5%AE%9A%E5%B8%86%E5%9C%B0%E4%BA%A7/081ea9e217686ed00eea28bf5a103512-599x450.jpg?t=1","https://pic1.ajkimg.com/display/anjuke/088f76-%E5%AE%9A%E5%B8%86%E5%9C%B0%E4%BA%A7/c23dc0aea062af93c9942e219e8e9b0e-599x450.jpg?t=1"]},{"title":"《一套别人都没有的房子》","key":"A966588886","href":"https://jx.anjuke.com/prop/view/A966588886","details":{"home":"3室2厅","floor":"高层(共18层)","buildyear":2016},"area":138,"totalprice":190,"unitprice":13768,"date":"2017-9-13","imgs":["https://pic1.ajkimg.com/display/anjuke/66c178-%E7%8B%AC%E7%AB%8B%E7%BB%8F%E7%BA%AA%E4%BA%BA/56ca9d83412c0998e18fda29f593aab8-599x450.jpg?t=1","https://pic1.ajkimg.com/display/anjuke/b139d2-%E7%8B%AC%E7%AB%8B%E7%BB%8F%E7%BA%AA%E4%BA%BA/58f9bf53f74d66b3d277357ea29cf85f-599x450.jpg?t=1","https://pic1.ajkimg.com/display/anjuke/3f1e8d-%E7%8B%AC%E7%AB%8B%E7%BB%8F%E7%BA%AA%E4%BA%BA/69caa732be6edb7f89755d35ca47d7a4-599x450.jpg?t=1","https://pic1.ajkimg.com/display/anjuke/ace14f-%E7%8B%AC%E7%AB%8B%E7%BB%8F%E7%BA%AA%E4%BA%BA/1dfab5d1f2b87a12813d34f3d1d2e2a5-599x450.jpg?t=1","https://pic1.ajkimg.com/display/anjuke/ffe0f7-%E7%8B%AC%E7%AB%8B%E7%BB%8F%E7%BA%AA%E4%BA%BA/e735e507a0d96f6ceaca4f2520af513c-599x450.jpg?t=1","https://pic1.ajkimg.com/display/anjuke/04efc7-%E7%8B%AC%E7%AB%8B%E7%BB%8F%E7%BA%AA%E4%BA%BA/a3e29e33706f93624acf3bba336f0095-599x450.jpg?t=1","https://pic1.ajkimg.com/display/anjuke/8ca51b-%E7%8B%AC%E7%AB%8B%E7%BB%8F%E7%BA%AA%E4%BA%BA/ea22d287d9aa258e99588729b71e80ae-599x450.jpg?t=1","https://pic1.ajkimg.com/display/anjuke/d8d065-%E7%8B%AC%E7%AB%8B%E7%BB%8F%E7%BA%AA%E4%BA%BA/8bfc1ece5bd564a472b4c0fc57fc3fd4-599x450.jpg?t=1","https://pic1.ajkimg.com/display/anjuke/a8479f-%E7%8B%AC%E7%AB%8B%E7%BB%8F%E7%BA%AA%E4%BA%BA/1dc692f532ddfa959742856abd59d046-599x450.jpg?t=1"]},{"title":"万达旁边 嘉兴实验学校 东北师范大学附属学校 到地铁口1公里","key":"A966547284","href":"https://jx.anjuke.com/prop/view/A966547284","details":{"home":"3室2厅","floor":"高层(共18层)","buildyear":2016},"area":125,"totalprice":140,"unitprice":11200,"date":"2017-9-13","imgs":["https://pic1.ajkimg.com/display/anjuke/030cd9-%E4%B8%8A%E6%B5%B7%E9%AD%85%E6%99%9F%E6%88%BF%E5%9C%B0%E4%BA%A7/e1ed2441e3e274cef038f16757300850-599x450.jpg?t=1","https://pic1.ajkimg.com/display/anjuke/d9d9d0-%E4%B8%8A%E6%B5%B7%E9%AD%85%E6%99%9F%E6%88%BF%E5%9C%B0%E4%BA%A7/91f596298f592dea0c352022581fda20-599x450.jpg?t=1","https://pic1.ajkimg.com/display/anjuke/620c5e-%E4%B8%8A%E6%B5%B7%E9%AD%85%E6%99%9F%E6%88%BF%E5%9C%B0%E4%BA%A7/4ee0f6ced7bc47f7cc899d44c28f98d7-599x450.jpg?t=1","https://pic1.ajkimg.com/display/anjuke/f2f7d9-%E4%B8%8A%E6%B5%B7%E9%AD%85%E6%99%9F%E6%88%BF%E5%9C%B0%E4%BA%A7/c5955c4c346f95273d13d223009cde8d-599x450.jpg?t=1","https://pic1.ajkimg.com/display/anjuke/acb012-%E4%B8%8A%E6%B5%B7%E9%AD%85%E6%99%9F%E6%88%BF%E5%9C%B0%E4%BA%A7/af870a376ba584eb588f0def3b46dc0e-599x450.jpg?t=1","https://pic1.ajkimg.com/display/anjuke/b3759f-%E4%B8%8A%E6%B5%B7%E9%AD%85%E6%99%9F%E6%88%BF%E5%9C%B0%E4%BA%A7/a7649e6b34c2ca0ae7c5845aac0f3c39-599x450.jpg?t=1","https://pic1.ajkimg.com/display/anjuke/8781db-%E4%B8%8A%E6%B5%B7%E9%AD%85%E6%99%9F%E6%88%BF%E5%9C%B0%E4%BA%A7/ea68b4392d95fb9933cb3fb9060b8820-599x450.jpg?t=1"]},{"title":"万达商圈+东北师大+嘉兴实验学校+清华大学附属实验小学","key":"A966530931","href":"https://jx.anjuke.com/prop/view/A966530931","details":{"home":"2室2厅","floor":"中层(共18层)","buildyear":2016},"area":93,"totalprice":100,"unitprice":10752,"date":"2017-9-13","imgs":["https://pic1.ajkimg.com/display/anjuke/41e119-%E4%B8%8A%E6%B5%B7%E9%AD%85%E6%99%9F%E6%88%BF%E5%9C%B0%E4%BA%A7/99fcb596e8fd61f83ba346e08887407d-599x450.jpg?t=1","https://pic1.ajkimg.com/display/anjuke/4be2c2-%E4%B8%8A%E6%B5%B7%E9%AD%85%E6%99%9F%E6%88%BF%E5%9C%B0%E4%BA%A7/7afc1b86167b7f30b1c45ca6eb698f6b-599x450.jpg?t=1","https://pic1.ajkimg.com/display/anjuke/396702-%E4%B8%8A%E6%B5%B7%E9%AD%85%E6%99%9F%E6%88%BF%E5%9C%B0%E4%BA%A7/80a365849c4d9cbb78d835d0fc59cfa2-599x450.jpg?t=1","https://pic1.ajkimg.com/display/anjuke/bbee0b-%E4%B8%8A%E6%B5%B7%E9%AD%85%E6%99%9F%E6%88%BF%E5%9C%B0%E4%BA%A7/4b80cff98856af210db68b3d1f9924f8-599x450.jpg?t=1","https://pic1.ajkimg.com/display/anjuke/48d672-%E4%B8%8A%E6%B5%B7%E9%AD%85%E6%99%9F%E6%88%BF%E5%9C%B0%E4%BA%A7/9eadc65f70178fb98daed8787534b892-599x450.jpg?t=1","https://pic1.ajkimg.com/display/anjuke/f704be-%E4%B8%8A%E6%B5%B7%E9%AD%85%E6%99%9F%E6%88%BF%E5%9C%B0%E4%BA%A7/3e1fe122a14a4428bbc6f711ec469bdd-599x450.jpg?t=1"]},{"title":"豪华装修 拎包入住 真正的地铁楼盘 升 值空间无限","key":"A966506159","href":"https://jx.anjuke.com/prop/view/A966506159","details":{"home":"2室2厅","floor":"低层(共18层)","buildyear":2016},"area":88,"totalprice":95,"unitprice":10795,"date":"2017-9-13","imgs":["https://pic1.ajkimg.com/display/anjuke/8d0825-%E4%B8%8A%E6%B5%B7%E9%AD%85%E6%99%9F%E6%88%BF%E5%9C%B0%E4%BA%A7/aaed2b9266ebc46f29ef298bff484e5e-599x450.jpg?t=1","https://pic1.ajkimg.com/display/anjuke/4ba726-%E4%B8%8A%E6%B5%B7%E9%AD%85%E6%99%9F%E6%88%BF%E5%9C%B0%E4%BA%A7/b6a3a4dfc614ec6cd04df030696fc856-599x450.jpg?t=1","https://pic1.ajkimg.com/display/anjuke/889c53-%E4%B8%8A%E6%B5%B7%E9%AD%85%E6%99%9F%E6%88%BF%E5%9C%B0%E4%BA%A7/2869fffa5f55ae41dbb6f77f45b79c0a-599x450.jpg?t=1","https://pic1.ajkimg.com/display/anjuke/878736-%E4%B8%8A%E6%B5%B7%E9%AD%85%E6%99%9F%E6%88%BF%E5%9C%B0%E4%BA%A7/7cd10bf04fb44da72dbec8143bb35a3b-599x450.jpg?t=1","https://pic1.ajkimg.com/display/anjuke/cfc1ee-%E4%B8%8A%E6%B5%B7%E9%AD%85%E6%99%9F%E6%88%BF%E5%9C%B0%E4%BA%A7/3752772cd1664b0d5fdabaac624d9b86-599x450.jpg?t=1","https://pic1.ajkimg.com/display/anjuke/77e692-%E4%B8%8A%E6%B5%B7%E9%AD%85%E6%99%9F%E6%88%BF%E5%9C%B0%E4%BA%A7/cf0b3173fcd8d3a155f68eac20ae6293-599x450.jpg?t=1","https://pic1.ajkimg.com/display/anjuke/45a1c3-%E4%B8%8A%E6%B5%B7%E9%AD%85%E6%99%9F%E6%88%BF%E5%9C%B0%E4%BA%A7/9e1ff873bccd915d0a549ba4f1ac6af9-599x450.jpg?t=1"]},{"title":"70万精装，品牌家电，交通便利，商业繁华，房东急售！","key":"A966435427","href":"https://jx.anjuke.com/prop/view/A966435427","details":{"home":"2室2厅","floor":"中层(共16层)","buildyear":2012},"area":83,"totalprice":70,"unitprice":8433,"date":"2017-9-13","imgs":["https://pic1.ajkimg.com/display/anjuke/c6ba54-%E7%8B%AC%E7%AB%8B%E7%BB%8F%E7%BA%AA%E4%BA%BA/fa8eecda5922ff7e3da395cac3527c79-599x450.jpg?t=1","https://pic1.ajkimg.com/display/anjuke/7c0299-%E7%8B%AC%E7%AB%8B%E7%BB%8F%E7%BA%AA%E4%BA%BA/a042d09b47d20b17418ebd8b5292170a-599x450.jpg?t=1","https://pic1.ajkimg.com/display/anjuke/318cab-%E7%8B%AC%E7%AB%8B%E7%BB%8F%E7%BA%AA%E4%BA%BA/66060742d779e376500d9292f0280822-599x450.jpg?t=1","https://pic1.ajkimg.com/display/anjuke/9355a2-%E7%8B%AC%E7%AB%8B%E7%BB%8F%E7%BA%AA%E4%BA%BA/3413b6309f09260ef4ca68460bdd4a32-599x450.jpg?t=1","https://pic1.ajkimg.com/display/anjuke/fb0ba2-%E7%8B%AC%E7%AB%8B%E7%BB%8F%E7%BA%AA%E4%BA%BA/cddab6209aa165742eb4b0faa914f336-599x450.jpg?t=1","https://pic1.ajkimg.com/display/anjuke/baae24-%E7%8B%AC%E7%AB%8B%E7%BB%8F%E7%BA%AA%E4%BA%BA/54e07ec478826c347d18738efcb1f258-599x450.jpg?t=1","https://pic1.ajkimg.com/display/anjuke/9925b7-%E7%8B%AC%E7%AB%8B%E7%BB%8F%E7%BA%AA%E4%BA%BA/a10af41ca25f21208dbb490d78968ba5-599x450.jpg?t=1","https://pic1.ajkimg.com/display/anjuke/1464c7-%E7%8B%AC%E7%AB%8B%E7%BB%8F%E7%BA%AA%E4%BA%BA/421e6d39067581bf17e1cd1a07ca7333-599x450.jpg?t=1"]}],"trend":{"community":[{"201410":"0"},{"201411":"0"},{"201412":"0"},{"201501":"0"},{"201502":"0"},{"201503":"0"},{"201504":"0"},{"201505":"0"},{"201506":"0"},{"201507":"0"},{"201508":"0"},{"201509":"0"},{"201510":"0"},{"201511":"0"},{"201512":"0"},{"201601":"0"},{"201602":"0"},{"201603":"0"},{"201604":"0"},{"201605":"7291"},{"201606":"7303"},{"201607":"7706"},{"201608":"8004"},{"201609":"8564"},{"201610":"10143"},{"201611":"11171"},{"201612":"10732"},{"201701":"10529"},{"201702":"10978"},{"201703":"10890"},{"201704":"12049"},{"201705":"12907"},{"201706":"13911"},{"201707":"14591"},{"201708":"14671"},{"201709":"14635"}],"area":[{"201410":"7390"},{"201411":"7801"},{"201412":"0"},{"201501":"0"},{"201502":"0"},{"201503":"0"},{"201504":"4482"},{"201505":"5888"},{"201506":"6049"},{"201507":"7316"},{"201508":"6928"},{"201509":"6286"},{"201510":"6410"},{"201511":"6666"},{"201512":"4259"},{"201601":"6076"},{"201602":"5709"},{"201603":"5833"},{"201604":"6520"},{"201605":"7164"},{"201606":"7142"},{"201607":"7142"},{"201608":"7507"},{"201609":"7818"},{"201610":"9042"},{"201611":"9590"},{"201612":"9079"},{"201701":"9209"},{"201702":"9366"},{"201703":"9901"},{"201704":"9666"},{"201705":"10343"},{"201706":"10512"},{"201707":"10839"},{"201708":"11062"},{"201709":"11226"}],"comm_midchange":"-0.00245382","area_midchange":"0.0148255"}},"jntyc":{"name":"江南太阳城","list":[{"title":"架空1楼带电梯，紧邻月河景区，采光好，精装全送！诚心可谈！","key":"A967029491","href":"https://jx.anjuke.com/prop/view/A967029491","details":{"home":"3室2厅","floor":"低层(共6层)","buildyear":2008},"area":94,"totalprice":136,"unitprice":14468,"date":"2017-9-13","imgs":["https://pic1.ajkimg.com/display/anjuke/07c029-%E5%AE%9D%E5%8A%B2%E6%88%BF%E4%BA%A7/81b28fbe5f3619d22c2e5a9c799211d5-599x450.jpg?t=1","https://pic1.ajkimg.com/display/anjuke/9a9a31-%E5%AE%9D%E5%8A%B2%E6%88%BF%E4%BA%A7/4c199858645e0b67aedb1e4e55e35503-599x450.jpg?t=1","https://pic1.ajkimg.com/display/anjuke/c3051b-%E5%AE%9D%E5%8A%B2%E6%88%BF%E4%BA%A7/cf92319987ae9311dbbd7d123f8653bf-599x450.jpg?t=1","https://pic1.ajkimg.com/display/anjuke/29833e-%E5%AE%9D%E5%8A%B2%E6%88%BF%E4%BA%A7/871e31774a2bddd3b297b242893794b6-599x450.jpg?t=1","https://pic1.ajkimg.com/display/anjuke/9ed5c7-%E5%AE%9D%E5%8A%B2%E6%88%BF%E4%BA%A7/758ca696637bacd5223e49c76c4eebac-599x450.jpg?t=1","https://pic1.ajkimg.com/display/anjuke/d33878-%E5%AE%9D%E5%8A%B2%E6%88%BF%E4%BA%A7/01ed1fee2b20656b6ebad408f0f0f5b7-599x450.jpg?t=1"]},{"title":"江南 94平方 108万 满2年","key":"A966348624","href":"https://jx.anjuke.com/prop/view/A966348624","details":{"home":"2室2厅","floor":"中层(共6层)","buildyear":2007},"area":94,"totalprice":108,"unitprice":11489,"date":"2017-9-13","imgs":["https://pic1.ajkimg.com/display/anjuke/d9c269-%E4%B8%8A%E6%BA%90%E5%9C%B0%E4%BA%A7/87939533c8c00f0676faf85340b6fa63-599x450.jpg?t=1","https://pic1.ajkimg.com/display/anjuke/fcc3e8-%E4%B8%8A%E6%BA%90%E5%9C%B0%E4%BA%A7/321e81abd5066fbca0f593025927e0ee-599x450.jpg?t=1","https://pic1.ajkimg.com/display/anjuke/b0322f-%E4%B8%8A%E6%BA%90%E5%9C%B0%E4%BA%A7/e5bfeeb5444c316c02d6bcac626b16c7-599x450.jpg?t=1","https://pic1.ajkimg.com/display/anjuke/cd23ab-%E4%B8%8A%E6%BA%90%E5%9C%B0%E4%BA%A7/eed314e773405088628c12c788ad2692-599x450.jpg?t=1","https://pic1.ajkimg.com/display/anjuke/133844-%E4%B8%8A%E6%BA%90%E5%9C%B0%E4%BA%A7/48ff8915b493c3b44c8de976b1f61ee6-599x450.jpg?t=1","https://pic1.ajkimg.com/display/anjuke/bce6dd-%E4%B8%8A%E6%BA%90%E5%9C%B0%E4%BA%A7/1f1d5d9825f133d10417413f9f3ce1d9-599x450.jpg?t=1","https://pic1.ajkimg.com/display/anjuke/6ab5a8-%E4%B8%8A%E6%BA%90%E5%9C%B0%E4%BA%A7/53b5dc39090d8d588b5bc797f7c63d63-599x450.jpg?t=1"]}],"trend":{"community":[{"201410":"6955"},{"201411":"7037"},{"201412":"7037"},{"201501":"7037"},{"201502":"7037"},{"201503":"7037"},{"201504":"7037"},{"201505":"7037"},{"201506":"7037"},{"201507":"7037"},{"201508":"7037"},{"201509":"7037"},{"201510":"7037"},{"201511":"7037"},{"201512":"7037"},{"201601":"7037"},{"201602":"7037"},{"201603":"7037"},{"201604":"7037"},{"201605":"7732"},{"201606":"7400"},{"201607":"7400"},{"201608":"7307"},{"201609":"8137"},{"201610":"9039"},{"201611":"9398"},{"201612":"8999"},{"201701":"8822"},{"201702":"9020"},{"201703":"9377"},{"201704":"9616"},{"201705":"9741"},{"201706":"11084"},{"201707":"12052"},{"201708":"11717"},{"201709":"12119"}],"area":[{"201410":"7390"},{"201411":"7801"},{"201412":"0"},{"201501":"0"},{"201502":"0"},{"201503":"0"},{"201504":"4482"},{"201505":"5888"},{"201506":"6049"},{"201507":"7316"},{"201508":"6928"},{"201509":"6286"},{"201510":"6410"},{"201511":"6666"},{"201512":"4259"},{"201601":"6076"},{"201602":"5709"},{"201603":"5833"},{"201604":"6520"},{"201605":"7164"},{"201606":"7142"},{"201607":"7142"},{"201608":"7507"},{"201609":"7818"},{"201610":"9042"},{"201611":"9590"},{"201612":"9079"},{"201701":"9209"},{"201702":"9366"},{"201703":"9901"},{"201704":"9666"},{"201705":"10343"},{"201706":"10512"},{"201707":"10839"},{"201708":"11062"},{"201709":"11226"}],"comm_midchange":"0.0343682","area_midchange":"0.0148255"}},"zgtjgjc-hcy":{"name":"中国铁建国际城和畅园","list":[{"title":"庐阳区高档小区中铁和畅园+5楼3室89平136万精装无税急卖","key":"A967025016","href":"https://hf.anjuke.com/prop/view/A967025016","details":{"home":"3室2厅","floor":"低层(共23层)","buildyear":2014},"area":89,"totalprice":136,"unitprice":15280,"date":"2017-9-13","imgs":["https://pic1.ajkimg.com/display/anjuke/0b9a47-%E8%BE%89%E8%BE%BE%E6%88%BF%E4%BA%A7/cb4bc9a7889f8bc12c80ce7a6996c3ef-599x450.jpg?t=1","https://pic1.ajkimg.com/display/anjuke/921e73-%E8%BE%89%E8%BE%BE%E6%88%BF%E4%BA%A7/00560ae5dfd624b8b80f832506a4ff3b-599x450.jpg?t=1","https://pic1.ajkimg.com/display/anjuke/543407-%E8%BE%89%E8%BE%BE%E6%88%BF%E4%BA%A7/53e4cfcb1f7be9e4db87771a241ac8d7-599x450.jpg?t=1","https://pic1.ajkimg.com/display/anjuke/04cb2e-%E8%BE%89%E8%BE%BE%E6%88%BF%E4%BA%A7/b617d604cc105c3e274b00043dff2b10-599x450.jpg?t=1","https://pic1.ajkimg.com/display/anjuke/bd0f57-%E8%BE%89%E8%BE%BE%E6%88%BF%E4%BA%A7/bd49967e8750693ade87dbf7435e06b7-599x450.jpg?t=1"]},{"title":"中铁国际城德园 精装修 纯边户 拎包入住","key":"A966998284","href":"https://hf.anjuke.com/prop/view/A966998284","details":{"home":"3室2厅","floor":"高层(共34层)","buildyear":2013},"area":89,"totalprice":158,"unitprice":17628,"date":"2017-9-13","imgs":["https://pic1.ajkimg.com/display/anjuke/279794-%E9%93%BE%E5%AE%B6%E5%9C%B0%E4%BA%A7/3bc93bb91c4bc790cbb6783aa47b953b-599x450.jpg?t=1","https://pic1.ajkimg.com/display/anjuke/7e08ba-%E9%93%BE%E5%AE%B6%E5%9C%B0%E4%BA%A7/fcf750f993ca64d78d29012a020d64c2-599x450.jpg?t=1","https://pic1.ajkimg.com/display/anjuke/71c2a5-%E9%93%BE%E5%AE%B6%E5%9C%B0%E4%BA%A7/a401368fe6335d1d060657ed37f8a540-599x450.jpg?t=1","https://pic1.ajkimg.com/display/anjuke/3ae9db-%E9%93%BE%E5%AE%B6%E5%9C%B0%E4%BA%A7/fb78581d0b2ed70fd355fce998f9f6eb-599x450.jpg?t=1","https://pic1.ajkimg.com/display/anjuke/70d80f-%E9%93%BE%E5%AE%B6%E5%9C%B0%E4%BA%A7/f3d2483492746ab1068347fcb04ebe9c-599x450.jpg?t=1","https://pic1.ajkimg.com/display/anjuke/2323ea-%E9%93%BE%E5%AE%B6%E5%9C%B0%E4%BA%A7/be3adecb1c1b8b9a5112f7c40b60eecc-599x450.jpg?t=1","https://pic1.ajkimg.com/display/anjuke/366ff2-%E9%93%BE%E5%AE%B6%E5%9C%B0%E4%BA%A7/88f8e163f2b068218eb6bddc19a1e5cc-599x450.jpg?t=1","https://pic1.ajkimg.com/display/anjuke/0ec7cf-%E9%93%BE%E5%AE%B6%E5%9C%B0%E4%BA%A7/0e7b041377fc13efc1ffb65e58d72cbb-599x450.jpg?t=1","https://pic1.ajkimg.com/display/anjuke/fd67e8-%E9%93%BE%E5%AE%B6%E5%9C%B0%E4%BA%A7/45c88f8125dd5dbd4c2198272d01b197-599x450.jpg?t=1"]},{"title":"金屋不动产精.选 和畅园 婚房装修 家具家电全送 房东急售","key":"A966983937","href":"https://hf.anjuke.com/prop/view/A966983937","details":{"home":"3室2厅","floor":"中层(共34层)","buildyear":2014},"area":87,"totalprice":157,"unitprice":17942,"date":"2017-9-13","imgs":["https://pic1.ajkimg.com/display/anjuke/588b5f-/d93be4f9f84442c3a6576d30bd236ed1-599x450.jpg?t=1","https://pic1.ajkimg.com/display/anjuke/85bdcc-/2096fd2b817b8bbd98c194e959659a90-599x450.jpg?t=1","https://pic1.ajkimg.com/display/anjuke/ba8c9b-/bbca89fc75849757112c4a7ce621fb19-599x450.jpg?t=1","https://pic1.ajkimg.com/display/anjuke/0be6b2-/7dc3294f440410cf76dca3d573f5a310-599x450.jpg?t=1","https://pic1.ajkimg.com/display/anjuke/49ec59-/6380e8a75d55131fafc024a114cf9fdb-599x450.jpg?t=1","https://pic1.ajkimg.com/display/anjuke/84e5f9-/4a4663fb51159e045332ea971df629e7-599x450.jpg?t=1","https://pic1.ajkimg.com/display/anjuke/b1d4f4-/c281ea931b46295ff86910d538d7d139-599x450.jpg?t=1","https://pic1.ajkimg.com/display/anjuke/aa048f-/3e03ef42bdd58ddf93057bb12c820d4b-599x450.jpg?t=1","https://pic1.ajkimg.com/display/anjuke/77e005-/a9c127d1a9871575c3b579734269fe8a-599x450.jpg?t=1"]},{"title":"金屋不动产精.选广园两室 双阳台 全天采光 毛坯仅此一套","key":"A966983917","href":"https://hf.anjuke.com/prop/view/A966983917","details":{"home":"2室2厅","floor":"中层(共34层)","buildyear":2013},"area":85,"totalprice":127,"unitprice":14941,"date":"2017-9-13","imgs":["https://pic1.ajkimg.com/display/anjuke/364e9d-/4cc542ad0a1c9df95956d4ea860ee0db-599x450.jpg?t=1","https://pic1.ajkimg.com/display/anjuke/ac81ca-/64a8d90272495f8df76a1ccd37f57f68-599x450.jpg?t=1","https://pic1.ajkimg.com/display/anjuke/f8e60b-/77ee4222d37b6b904ba708ab77205df9-599x450.jpg?t=1","https://pic1.ajkimg.com/display/anjuke/b031b2-/74c92028fac0ab87363ec17e74aa2e96-599x450.jpg?t=1","https://pic1.ajkimg.com/display/anjuke/5a44e2-/4ebd8a3bcb64829765f6ad8e2ef8b2d1-599x450.jpg?t=1","https://pic1.ajkimg.com/display/anjuke/ce4cb6-/b49cf4b94d3590ab354ac68a36033691-599x450.jpg?t=1","https://pic1.ajkimg.com/display/anjuke/164502-/03a226d82ee60350a30ce70a030136e8-599x450.jpg?t=1","https://pic1.ajkimg.com/display/anjuke/63b518-/b2bc4b3be3ed31841551e3165f595d42-599x450.jpg?t=1","https://pic1.ajkimg.com/display/anjuke/65e28d-/3a3a6f31ee3f1bfc0be65de91dcf0cbe-599x450.jpg?t=1","https://pic1.ajkimg.com/display/anjuke/733b36-/20ace0c9465332c284402b612cc1dd9e-599x450.jpg?t=1"]},{"title":"中铁和畅园 边户三房 观景房 六安路小学 四十二中 无税","key":"A966983894","href":"https://hf.anjuke.com/prop/view/A966983894","details":{"home":"3室2厅","floor":"高层(共28层)","buildyear":2011},"area":100,"totalprice":136,"unitprice":13600,"date":"2017-9-13","imgs":["https://pic1.ajkimg.com/display/anjuke/8fa745-/a4f4a71aad5dc765b76a0db9f7498c09-599x450.jpg?t=1","https://pic1.ajkimg.com/display/anjuke/348f13-/4d3d97a686c5ec2cbc4f7bdc04155bdf-599x450.jpg?t=1","https://pic1.ajkimg.com/display/anjuke/77fb73-/425a1a528b43095fbfcb13ee6c3583df-599x450.jpg?t=1","https://pic1.ajkimg.com/display/anjuke/6c6714-/ead607a6ab929d99b8d42ac6ce47f78a-599x450.jpg?t=1","https://pic1.ajkimg.com/display/anjuke/f11d3d-/aee7d0515a4f3e4f218424e9a1694fbd-599x450.jpg?t=1","https://pic1.ajkimg.com/display/anjuke/ffdf78-/42fc47d8776a421724adeb5f75ff97b8-599x450.jpg?t=1","https://pic1.ajkimg.com/display/anjuke/4e0554-/6c67c8eea2cb0dac08181fcd3f217038-599x450.jpg?t=1","https://pic1.ajkimg.com/display/anjuke/520f10-/9bb1b130c082244279b0054051a0ea9e-599x450.jpg?t=1"]},{"title":"金屋不动产做* 边户大三房 降价10万 看房随时 急","key":"A966980901","href":"https://hf.anjuke.com/prop/view/A966980901","details":{"home":"3室2厅","floor":"高层(共34层)","buildyear":2015},"area":125,"totalprice":175,"unitprice":14000,"date":"2017-9-13","imgs":["https://pic1.ajkimg.com/display/anjuke/0c7520-/b78344efb696a89256fe1b4c4ab40d82-599x450.jpg?t=1","https://pic1.ajkimg.com/display/anjuke/1d804b-/a5c9a75e05310a0ab0d8e129f140a284-599x450.jpg?t=1","https://pic1.ajkimg.com/display/anjuke/a0793f-/b1373482cda3bb82da0efaa9c4b0eb29-599x450.jpg?t=1","https://pic1.ajkimg.com/display/anjuke/13b485-/e5b9ab819d0b7da956bdd4b355a7fe2c-599x450.jpg?t=1","https://pic1.ajkimg.com/display/anjuke/b6a02d-/9e2c69724299b1dde6c408d57f211459-599x450.jpg?t=1","https://pic1.ajkimg.com/display/anjuke/6c8de2-/6d12612139b0cbaef25de79c502e8859-599x450.jpg?t=1","https://pic1.ajkimg.com/display/anjuke/51ccd0-/caa7478676f454210972049b793c7e32-599x450.jpg?t=1","https://pic1.ajkimg.com/display/anjuke/19d72f-/039bd640d51e9cd245ce2bccf86d3c3f-599x450.jpg?t=1","https://pic1.ajkimg.com/display/anjuke/7d7dbb-/dc1af06b941746a710e0a858f4f093b8-599x450.jpg?t=1","https://pic1.ajkimg.com/display/anjuke/1222a4-/979ead538ebf87ab7382d7696233124c-599x450.jpg?t=1"]},{"title":"中铁国际城和畅园、精装房、六安路小学、42中学、看房随时","key":"A966980876","href":"https://hf.anjuke.com/prop/view/A966980876","details":{"home":"3室2厅","floor":"高层(共25层)","buildyear":2013},"area":90,"totalprice":140,"unitprice":15555,"date":"2017-9-13","imgs":["https://pic1.ajkimg.com/display/anjuke/4a3b41-/138648ff84cf6fa06a80988d2708fc67-599x450.jpg?t=1","https://pic1.ajkimg.com/display/anjuke/9eb8c3-/26dc40ab7d9719455a063b8c4a634854-599x450.jpg?t=1","https://pic1.ajkimg.com/display/anjuke/5bc492-/b448b8af8ba53d49f05c2ccb5a1e99fa-599x450.jpg?t=1","https://pic1.ajkimg.com/display/anjuke/2cb0f8-/a09aa0511f471e28cd366f2d1cd14e58-599x450.jpg?t=1","https://pic1.ajkimg.com/display/anjuke/5afc61-/b6e863731caf3ca94cb2e5df772122ab-599x450.jpg?t=1","https://pic1.ajkimg.com/display/anjuke/5880f7-/04bb6eda7965177e18c36776d4fb507c-599x450.jpg?t=1","https://pic1.ajkimg.com/display/anjuke/258736-/5a18f742c843358b588cf3c0a565c6ee-599x450.jpg?t=1","https://pic1.ajkimg.com/display/anjuke/30687b-/0702f2cd48abe943b648b75e9339b9a4-599x450.jpg?t=1"]},{"title":"中铁国际城《和畅园+豪装三室六阳台+采光全天》急售！随时看房","key":"A966980856","href":"https://hf.anjuke.com/prop/view/A966980856","details":{"home":"3室2厅","floor":"高层(共34层)","buildyear":2014},"area":128,"totalprice":188,"unitprice":14687,"date":"2017-9-13","imgs":["https://pic1.ajkimg.com/display/anjuke/010f7a-/311b9e1a7414f84debfbdd3af1b09f21-599x450.jpg?t=1","https://pic1.ajkimg.com/display/anjuke/4d366a-/b48811a786d769ee1ed2d472eb234d3c-599x450.jpg?t=1","https://pic1.ajkimg.com/display/anjuke/b6021d-/33fb6e18bfb1de7e8b3f682303c5dbfa-599x450.jpg?t=1","https://pic1.ajkimg.com/display/anjuke/ef1afd-/92c892c919c4ea8a7284ae9ca70c6a8f-599x450.jpg?t=1","https://pic1.ajkimg.com/display/anjuke/db89eb-/bdf176d2c3b5bde0961894fee144cf17-599x450.jpg?t=1","https://pic1.ajkimg.com/display/anjuke/3f701e-/760ea48f91e7bd6fb51dbf3d5950cf00-599x450.jpg?t=1","https://pic1.ajkimg.com/display/anjuke/6e5745-/b92645d2fc9ea31882e09a84bb37ad22-599x450.jpg?t=1","https://pic1.ajkimg.com/display/anjuke/a6ca1e-/5a29a54d17a9e7c927e9333b9562c502-599x450.jpg?t=1","https://pic1.ajkimg.com/display/anjuke/1776b7-/50a2c13a6648b543f51ee6727b96d367-599x450.jpg?t=1"]},{"title":"中铁国际城和畅园、精装房、六安路小学、42中学、看房随时","key":"A966980861","href":"https://hf.anjuke.com/prop/view/A966980861","details":{"home":"4室2厅","floor":"高层(共25层)","buildyear":2013},"area":123,"totalprice":180,"unitprice":14634,"date":"2017-9-13","imgs":["https://pic1.ajkimg.com/display/anjuke/4a3b41-/138648ff84cf6fa06a80988d2708fc67-599x450.jpg?t=1","https://pic1.ajkimg.com/display/anjuke/9eb8c3-/26dc40ab7d9719455a063b8c4a634854-599x450.jpg?t=1","https://pic1.ajkimg.com/display/anjuke/5bc492-/b448b8af8ba53d49f05c2ccb5a1e99fa-599x450.jpg?t=1","https://pic1.ajkimg.com/display/anjuke/2cb0f8-/a09aa0511f471e28cd366f2d1cd14e58-599x450.jpg?t=1","https://pic1.ajkimg.com/display/anjuke/5afc61-/b6e863731caf3ca94cb2e5df772122ab-599x450.jpg?t=1","https://pic1.ajkimg.com/display/anjuke/5880f7-/04bb6eda7965177e18c36776d4fb507c-599x450.jpg?t=1","https://pic1.ajkimg.com/display/anjuke/258736-/5a18f742c843358b588cf3c0a565c6ee-599x450.jpg?t=1","https://pic1.ajkimg.com/display/anjuke/30687b-/0702f2cd48abe943b648b75e9339b9a4-599x450.jpg?t=1"]},{"title":" 中铁和畅园，满两年，精装湖景房，南北通透","key":"A966966711","href":"https://hf.anjuke.com/prop/view/A966966711","details":{"home":"3室2厅","floor":"中层(共34层)","buildyear":2014},"area":85,"totalprice":160,"unitprice":18823,"date":"2017-9-13","imgs":["https://pic1.ajkimg.com/display/anjuke/ebd588-%E9%93%BE%E5%AE%B6%E5%9C%B0%E4%BA%A7/3582e1c3c6fec85650422c9aecc5db15-599x450.jpg?t=1","https://pic1.ajkimg.com/display/anjuke/43f90b-%E9%93%BE%E5%AE%B6%E5%9C%B0%E4%BA%A7/835f7123412d61e8436d468bf609bb57-599x450.jpg?t=1","https://pic1.ajkimg.com/display/anjuke/ad3b7f-%E9%93%BE%E5%AE%B6%E5%9C%B0%E4%BA%A7/fb718ae95bf7fa40c694649b8d71071c-599x450.jpg?t=1","https://pic1.ajkimg.com/display/anjuke/19fe3d-%E9%93%BE%E5%AE%B6%E5%9C%B0%E4%BA%A7/1e050daa7aa3ac7349703f9ffda159df-599x450.jpg?t=1","https://pic1.ajkimg.com/display/anjuke/30f77e-%E9%93%BE%E5%AE%B6%E5%9C%B0%E4%BA%A7/3599b52b94184e4a852887e3d700bc95-599x450.jpg?t=1","https://pic1.ajkimg.com/display/anjuke/116333-%E9%93%BE%E5%AE%B6%E5%9C%B0%E4%BA%A7/2daf9bf2cd6eb1f581e4da70c2a3ac2d-599x450.jpg?t=1"]},{"title":"中铁和畅园 精装大三房 业主急售 单价不单一万五 随时可看！","key":"A966966578","href":"https://hf.anjuke.com/prop/view/A966966578","details":{"home":"3室2厅","floor":"高层(共28层)","buildyear":2013},"area":83,"totalprice":122,"unitprice":14593,"date":"2017-9-13","imgs":["https://pic1.ajkimg.com/display/anjuke/1d787c-%E9%93%BE%E5%AE%B6%E5%9C%B0%E4%BA%A7/d1b833655b2f3b8ab955659c4c392ecf-599x450.jpg?t=1","https://pic1.ajkimg.com/display/anjuke/f782c0-%E9%93%BE%E5%AE%B6%E5%9C%B0%E4%BA%A7/364b03ec08895454f2f40fc58d775c5c-599x450.jpg?t=1","https://pic1.ajkimg.com/display/anjuke/474aca-%E9%93%BE%E5%AE%B6%E5%9C%B0%E4%BA%A7/8739e258c7b29b869cb7dc5e38e1e0b0-599x450.jpg?t=1","https://pic1.ajkimg.com/display/anjuke/5c3354-%E9%93%BE%E5%AE%B6%E5%9C%B0%E4%BA%A7/23910da11d5fc9a924c160697b82a28e-599x450.jpg?t=1","https://pic1.ajkimg.com/display/anjuke/f50107-%E9%93%BE%E5%AE%B6%E5%9C%B0%E4%BA%A7/8dd0475bfe0cf01e4da391f40e73d93b-599x450.jpg?t=1","https://pic1.ajkimg.com/display/anjuke/1fd0f7-%E9%93%BE%E5%AE%B6%E5%9C%B0%E4%BA%A7/830cca21cd28b87e093a0f69c79b9545-599x450.jpg?t=1","https://pic1.ajkimg.com/display/anjuke/144524-%E9%93%BE%E5%AE%B6%E5%9C%B0%E4%BA%A7/86d679c946cdeb7cb13f2ee89d22b3f1-599x450.jpg?t=1","https://pic1.ajkimg.com/display/anjuke/87b6ba-%E9%93%BE%E5%AE%B6%E5%9C%B0%E4%BA%A7/f0bfe9d6dd345dcd43da4763bb86aef9-599x450.jpg?t=1","https://pic1.ajkimg.com/display/anjuke/07fc8f-%E9%93%BE%E5%AE%B6%E5%9C%B0%E4%BA%A7/ced4e85f06ee41641d59237d74249ae5-599x450.jpg?t=1"]},{"title":"《义*和优选房》精装3房 六安路小学+42中 无税 全天采光","key":"A966880595","href":"https://hf.anjuke.com/prop/view/A966880595","details":{"home":"3室2厅","floor":"高层(共34层)","buildyear":2011},"area":86,"totalprice":130,"unitprice":15116,"date":"2017-9-13","imgs":["https://pic1.ajkimg.com/display/anjuke/bdf05e-%E4%B9%89%E5%92%8C%E6%88%BF%E5%9C%B0%E4%BA%A7/1b9c2bb8c500456c23075d9ab416b239-599x450.jpg?t=1","https://pic1.ajkimg.com/display/anjuke/21a4ef-%E4%B9%89%E5%92%8C%E6%88%BF%E5%9C%B0%E4%BA%A7/6b85487bd804352ddefbfd8a5bf2815c-599x450.jpg?t=1","https://pic1.ajkimg.com/display/anjuke/e9bbd6-%E4%B9%89%E5%92%8C%E6%88%BF%E5%9C%B0%E4%BA%A7/b09a1583ae3858f2a026aa0db20b6a3e-599x450.jpg?t=1","https://pic1.ajkimg.com/display/anjuke/c9ee9c-%E4%B9%89%E5%92%8C%E6%88%BF%E5%9C%B0%E4%BA%A7/c6996361d9d91b82d30e3aa0033a641b-599x450.jpg?t=1","https://pic1.ajkimg.com/display/anjuke/fe24ac-%E4%B9%89%E5%92%8C%E6%88%BF%E5%9C%B0%E4%BA%A7/f8d3b107d8582459d278e0ba8f7d37b8-599x450.jpg?t=1","https://pic1.ajkimg.com/display/anjuke/689cc3-%E4%B9%89%E5%92%8C%E6%88%BF%E5%9C%B0%E4%BA%A7/032987b1b91c1b2a8398f1aa5dfa2055-599x450.jpg?t=1"]},{"title":"中国铁建国际城和畅园.精装修，六安路小学！","key":"A966832687","href":"https://hf.anjuke.com/prop/view/A966832687","details":{"home":"3室2厅","floor":"中层(共34层)","buildyear":2014},"area":90,"totalprice":136,"unitprice":15111,"date":"2017-9-13","imgs":["https://pic1.ajkimg.com/display/anjuke/202dd9-%E5%90%88%E8%81%94%E5%9C%B0%E4%BA%A7/58aa9f74bad885c13340ed0da39c6d9a-599x450.jpg?t=1","https://pic1.ajkimg.com/display/anjuke/13bc04-%E5%90%88%E8%81%94%E5%9C%B0%E4%BA%A7/e78236a6a4fe43dd0d5cc7b7c5b2343b-599x450.jpg?t=1","https://pic1.ajkimg.com/display/anjuke/982e7c-%E5%90%88%E8%81%94%E5%9C%B0%E4%BA%A7/e3fa398bb1704fd40de605db37df5080-599x450.jpg?t=1","https://pic1.ajkimg.com/display/anjuke/9c9981-%E5%90%88%E8%81%94%E5%9C%B0%E4%BA%A7/e7e0f6d2b78ce5b2ba19a55821070c21-599x450.jpg?t=1"]},{"title":" 中铁国际城和畅园  三居室精装修","key":"A966752903","href":"https://hf.anjuke.com/prop/view/A966752903","details":{"home":"3室2厅","floor":"高层(共30层)","buildyear":2013},"area":86,"totalprice":138,"unitprice":15985,"date":"2017-9-13","imgs":["https://pic1.ajkimg.com/display/anjuke/fb85c7-%E9%93%BE%E5%AE%B6%E5%9C%B0%E4%BA%A7/4599c7cde7fca1922b154beda82e8a08-599x450.jpg?t=1","https://pic1.ajkimg.com/display/anjuke/351777-%E9%93%BE%E5%AE%B6%E5%9C%B0%E4%BA%A7/b6171da5aab0f35d4c63dbe277c58e20-599x450.jpg?t=1","https://pic1.ajkimg.com/display/anjuke/911deb-%E9%93%BE%E5%AE%B6%E5%9C%B0%E4%BA%A7/423a1a90fa02e635ec1670bdde26fea3-599x450.jpg?t=1","https://pic1.ajkimg.com/display/anjuke/3f285e-%E9%93%BE%E5%AE%B6%E5%9C%B0%E4%BA%A7/643ae306a4833ca70e76a74caf0eb415-599x450.jpg?t=1","https://pic1.ajkimg.com/display/anjuke/21fce2-%E9%93%BE%E5%AE%B6%E5%9C%B0%E4%BA%A7/9cda5bb353308154e60436fc29aa3536-599x450.jpg?t=1","https://pic1.ajkimg.com/display/anjuke/d21dc8-%E9%93%BE%E5%AE%B6%E5%9C%B0%E4%BA%A7/bc8e06223301b28f9b896bcbe2153688-599x450.jpg?t=1","https://pic1.ajkimg.com/display/anjuke/645a13-%E9%93%BE%E5%AE%B6%E5%9C%B0%E4%BA%A7/19313bcdc949cf69af7738a78e3095b6-599x450.jpg?t=1","https://pic1.ajkimg.com/display/anjuke/071410-%E9%93%BE%E5%AE%B6%E5%9C%B0%E4%BA%A7/82aab8d5c986964395b946a19eca4876-599x450.jpg?t=1"]},{"title":" 中铁国际城和畅园 3室2厅 89平","key":"A966746757","href":"https://hf.anjuke.com/prop/view/A966746757","details":{"home":"3室2厅","floor":"高层(共34层)","buildyear":2013},"area":89,"totalprice":158,"unitprice":17628,"date":"2017-9-13","imgs":["https://pic1.ajkimg.com/display/anjuke/279794-%E9%93%BE%E5%AE%B6%E5%9C%B0%E4%BA%A7/3bc93bb91c4bc790cbb6783aa47b953b-599x450.jpg?t=1","https://pic1.ajkimg.com/display/anjuke/71c2a5-%E9%93%BE%E5%AE%B6%E5%9C%B0%E4%BA%A7/a401368fe6335d1d060657ed37f8a540-599x450.jpg?t=1","https://pic1.ajkimg.com/display/anjuke/70d80f-%E9%93%BE%E5%AE%B6%E5%9C%B0%E4%BA%A7/f3d2483492746ab1068347fcb04ebe9c-599x450.jpg?t=1","https://pic1.ajkimg.com/display/anjuke/2323ea-%E9%93%BE%E5%AE%B6%E5%9C%B0%E4%BA%A7/be3adecb1c1b8b9a5112f7c40b60eecc-599x450.jpg?t=1","https://pic1.ajkimg.com/display/anjuke/7e08ba-%E9%93%BE%E5%AE%B6%E5%9C%B0%E4%BA%A7/fcf750f993ca64d78d29012a020d64c2-599x450.jpg?t=1","https://pic1.ajkimg.com/display/anjuke/3ae9db-%E9%93%BE%E5%AE%B6%E5%9C%B0%E4%BA%A7/fb78581d0b2ed70fd355fce998f9f6eb-599x450.jpg?t=1"]},{"title":"中铁物业租售中心力荐大四房，湖景房，有钥匙随时看房。","key":"A966734049","href":"https://hf.anjuke.com/prop/view/A966734049","details":{"home":"4室2厅","floor":"高层(共34层)","buildyear":2013},"area":149,"totalprice":230,"unitprice":15436,"date":"2017-9-13","imgs":["https://pic1.ajkimg.com/display/anjuke/c9197e-%E4%B8%AD%E9%93%81%E5%BB%BA/bbf21b73c762b1cfc62f498fa20a7f92-599x450.jpg?t=1","https://pic1.ajkimg.com/display/anjuke/3c2ceb-%E4%B8%AD%E9%93%81%E5%BB%BA/f92a275393963eaac8b1e85fa696f349-599x450.jpg?t=1","https://pic1.ajkimg.com/display/anjuke/22369e-%E4%B8%AD%E9%93%81%E5%BB%BA/f075ae833013bd618ccd90353d714faa-599x450.jpg?t=1","https://pic1.ajkimg.com/display/anjuke/1ac4e9-%E4%B8%AD%E9%93%81%E5%BB%BA/79ad48d3b3de59024e52ad84d276db90-599x450.jpg?t=1","https://pic1.ajkimg.com/display/anjuke/927b13-%E4%B8%AD%E9%93%81%E5%BB%BA/32a9cb524669219f6089ce5c89fe6615-599x450.jpg?t=1","https://pic1.ajkimg.com/display/anjuke/860f6b-%E4%B8%AD%E9%93%81%E5%BB%BA/998851093eea56293b27f0906a988161-599x450.jpg?t=1","https://pic1.ajkimg.com/display/anjuke/176f97-%E4%B8%AD%E9%93%81%E5%BB%BA/f040cb9a2389397119842bd32280e0b8-599x450.jpg?t=1","https://pic1.ajkimg.com/display/anjuke/0d5ec8-%E4%B8%AD%E9%93%81%E5%BB%BA/8380f08495af1a19e8ecc4bb2261eb7b-599x450.jpg?t=1"]},{"title":"中铁德园 大三室 南门小学 42中 婚房装修 房主急售","key":"A966618457","href":"https://hf.anjuke.com/prop/view/A966618457","details":{"home":"3室2厅","floor":"高层(共33层)","buildyear":2010},"area":89,"totalprice":153,"unitprice":17191,"date":"2017-9-13","imgs":["https://pic1.ajkimg.com/display/anjuke/8dbd78-/d460d314f1508d293028520faf25076b-599x450.jpg?t=1","https://pic1.ajkimg.com/display/anjuke/4d0794-/16aa0e0308d1110631b1024b291645ef-599x450.jpg?t=1","https://pic1.ajkimg.com/display/anjuke/14f01c-/b3d3662db11fa712691015ce2d2f94b2-599x450.jpg?t=1","https://pic1.ajkimg.com/display/anjuke/a72144-/ee9f2976e8f6cb89182e8d9a45c42ca6-599x450.jpg?t=1","https://pic1.ajkimg.com/display/anjuke/1f010b-/57a9358eef4bfa8ebea666d7d39686ba-599x450.jpg?t=1"]},{"title":" 精装修，采光无遮挡，小区环境干净，配套齐全","key":"A966560978","href":"https://hf.anjuke.com/prop/view/A966560978","details":{"home":"3室2厅","floor":"高层(共28层)","buildyear":2013},"area":83,"totalprice":122,"unitprice":14593,"date":"2017-9-13","imgs":["https://pic1.ajkimg.com/display/anjuke/1d787c-%E9%93%BE%E5%AE%B6%E5%9C%B0%E4%BA%A7/d1b833655b2f3b8ab955659c4c392ecf-599x450.jpg?t=1","https://pic1.ajkimg.com/display/anjuke/1fd0f7-%E9%93%BE%E5%AE%B6%E5%9C%B0%E4%BA%A7/830cca21cd28b87e093a0f69c79b9545-599x450.jpg?t=1","https://pic1.ajkimg.com/display/anjuke/474aca-%E9%93%BE%E5%AE%B6%E5%9C%B0%E4%BA%A7/8739e258c7b29b869cb7dc5e38e1e0b0-599x450.jpg?t=1","https://pic1.ajkimg.com/display/anjuke/144524-%E9%93%BE%E5%AE%B6%E5%9C%B0%E4%BA%A7/86d679c946cdeb7cb13f2ee89d22b3f1-599x450.jpg?t=1","https://pic1.ajkimg.com/display/anjuke/87b6ba-%E9%93%BE%E5%AE%B6%E5%9C%B0%E4%BA%A7/f0bfe9d6dd345dcd43da4763bb86aef9-599x450.jpg?t=1","https://pic1.ajkimg.com/display/anjuke/f50107-%E9%93%BE%E5%AE%B6%E5%9C%B0%E4%BA%A7/8dd0475bfe0cf01e4da391f40e73d93b-599x450.jpg?t=1","https://pic1.ajkimg.com/display/anjuke/f782c0-%E9%93%BE%E5%AE%B6%E5%9C%B0%E4%BA%A7/364b03ec08895454f2f40fc58d775c5c-599x450.jpg?t=1","https://pic1.ajkimg.com/display/anjuke/5c3354-%E9%93%BE%E5%AE%B6%E5%9C%B0%E4%BA%A7/23910da11d5fc9a924c160697b82a28e-599x450.jpg?t=1","https://pic1.ajkimg.com/display/anjuke/07fc8f-%E9%93%BE%E5%AE%B6%E5%9C%B0%E4%BA%A7/ced4e85f06ee41641d59237d74249ae5-599x450.jpg?t=1"]},{"title":"《义.和优选房》中铁国际城42中6小 硬装20万3房2厅急售","key":"A966412129","href":"https://hf.anjuke.com/prop/view/A966412129","details":{"home":"3室2厅","floor":"中层(共28层)","buildyear":2015},"area":89,"totalprice":138,"unitprice":15388,"date":"2017-9-13","imgs":["https://pic1.ajkimg.com/display/anjuke/dc974c-%E4%B9%89%E5%92%8C%E6%88%BF%E5%9C%B0%E4%BA%A7/65c8d1d61c479e58929a44522c082f43-599x450.jpg?t=1","https://pic1.ajkimg.com/display/anjuke/88f4d4-%E4%B9%89%E5%92%8C%E6%88%BF%E5%9C%B0%E4%BA%A7/d739a5e31660d6ba4b253160faba814d-599x450.jpg?t=1","https://pic1.ajkimg.com/display/anjuke/99b900-%E4%B9%89%E5%92%8C%E6%88%BF%E5%9C%B0%E4%BA%A7/e41bd505d9e0d37f8e06fa2620fcfc46-599x450.jpg?t=1","https://pic1.ajkimg.com/display/anjuke/6d2c2a-%E4%B9%89%E5%92%8C%E6%88%BF%E5%9C%B0%E4%BA%A7/268d6d8881a89351383ce1c8d1c2a7a7-599x450.jpg?t=1","https://pic1.ajkimg.com/display/anjuke/74697a-%E4%B9%89%E5%92%8C%E6%88%BF%E5%9C%B0%E4%BA%A7/1188083dc5f7ee52e6e9e434f3e89917-599x450.jpg?t=1","https://pic1.ajkimg.com/display/anjuke/da77b0-%E4%B9%89%E5%92%8C%E6%88%BF%E5%9C%B0%E4%BA%A7/7eb2b76d745bec9c4e16edbb3e1b7e94-599x450.jpg?t=1"]},{"title":"《义.和优选房》中铁和畅园品致小区 婚房装修20万3房2厅","key":"A966412158","href":"https://hf.anjuke.com/prop/view/A966412158","details":{"home":"3室2厅","floor":"中层(共24层)","buildyear":2015},"area":89,"totalprice":140,"unitprice":15609,"date":"2017-9-13","imgs":["https://pic1.ajkimg.com/display/anjuke/7fea83-%E4%B9%89%E5%92%8C%E6%88%BF%E5%9C%B0%E4%BA%A7/407c1e5acb3835e2a9910def1ca99361-599x450.jpg?t=1","https://pic1.ajkimg.com/display/anjuke/6cbdd4-%E4%B9%89%E5%92%8C%E6%88%BF%E5%9C%B0%E4%BA%A7/d9b58517c076cb08aa687d321f0c331c-599x450.jpg?t=1","https://pic1.ajkimg.com/display/anjuke/459523-%E4%B9%89%E5%92%8C%E6%88%BF%E5%9C%B0%E4%BA%A7/12c99f007e76cf94ee047efd9dc30076-599x450.jpg?t=1","https://pic1.ajkimg.com/display/anjuke/83417d-%E4%B9%89%E5%92%8C%E6%88%BF%E5%9C%B0%E4%BA%A7/2e04dd7240dce2a051cfbc8f2e67183e-599x450.jpg?t=1","https://pic1.ajkimg.com/display/anjuke/36b746-%E4%B9%89%E5%92%8C%E6%88%BF%E5%9C%B0%E4%BA%A7/8bd94143bf3c76bc9f1298b7400a1673-599x450.jpg?t=1"]}],"trend":{"community":[{"201410":"0"},{"201411":"0"},{"201412":"0"},{"201501":"0"},{"201502":"0"},{"201503":"0"},{"201504":"0"},{"201505":"0"},{"201506":"0"},{"201507":"0"},{"201508":"0"},{"201509":"0"},{"201510":"0"},{"201511":"0"},{"201512":"0"},{"201601":"0"},{"201602":"0"},{"201603":"0"},{"201604":"0"},{"201605":"0"},{"201606":"0"},{"201607":"0"},{"201608":"16550"},{"201609":"17142"},{"201610":"18332"},{"201611":"18092"},{"201612":"17993"},{"201701":"17633"},{"201702":"17521"},{"201703":"17517"},{"201704":"17086"},{"201705":"17073"},{"201706":"17027"},{"201707":"16924"},{"201708":"17020"},{"201709":"17184"}],"area":[{"201410":"6891"},{"201411":"6832"},{"201412":"6922"},{"201501":"7049"},{"201502":"6721"},{"201503":"7199"},{"201504":"7378"},{"201505":"7541"},{"201506":"7549"},{"201507":"7548"},{"201508":"7544"},{"201509":"7605"},{"201510":"7561"},{"201511":"7602"},{"201512":"8312"},{"201601":"8559"},{"201602":"8579"},{"201603":"9196"},{"201604":"10217"},{"201605":"10786"},{"201606":"11813"},{"201607":"12229"},{"201608":"13893"},{"201609":"16111"},{"201610":"16673"},{"201611":"16866"},{"201612":"16445"},{"201701":"16277"},{"201702":"15992"},{"201703":"16008"},{"201704":"15419"},{"201705":"15599"},{"201706":"15764"},{"201707":"15803"},{"201708":"15625"},{"201709":"15815"}],"comm_midchange":"0.0096538","area_midchange":"0.0122092"}}}