{"source":{"ajk":"安居客","fccs":"房产超市"},"day":[{"s":"ajk","c":"jy-dfds","a":12818,"p":-0.040568862275449105,"today":"2017-10-19"},{"s":"fccs","c":"jy-dfds","a":16467,"p":0.0005468465184104995,"today":"2017-10-19"},{"s":"ajk","c":"hrhy","today":"2017-10-19"},{"s":"fccs","c":"hrhy","a":14800,"p":-0.0008101539292465569,"today":"2017-10-19"},{"s":"ajk","c":"zgtjgjc-hcy","a":16036,"p":-0.019384822356754112,"today":"2017-10-19"},{"s":"fccs","c":"zgtjgjc-hcy","today":"2017-10-19"},{"s":"ajk","c":"jntyc","p":null,"today":"2017-10-19"},{"s":"fccs","c":"jntyc","a":12527,"p":0.001198849104859335,"today":"2017-10-19"}],"mon":[{"s":"ajk","c":"jy-dfds","a":14506,"p":-0.01847215643818932,"mon":"201710"},{"s":"fccs","c":"jy-dfds","a":16603,"p":-0.007056994198911548,"mon":"201710"},{"s":"ajk","c":"hrhy","a":14749,"p":0.0004748338081671415,"mon":"201710"},{"s":"fccs","c":"hrhy","a":14785,"p":-0.006718172657037286,"mon":"201710"},{"s":"ajk","c":"zgtjgjc-hcy","a":17077,"p":-0.003501196242049367,"mon":"201710"},{"s":"fccs","c":"zgtjgjc-hcy","mon":"201710"},{"s":"ajk","c":"jntyc","a":12803,"p":0.05054566341183228,"mon":"201710"},{"s":"fccs","c":"jntyc","a":12266,"p":0.014138073584125672,"mon":"201710"}]}